[
    {
        "id": "1",
        "name": "Test form",
        "description": "Form description",
        "questions": [
            {
                "id": "402a1459-f7cf-42f7-8d56-dfc100adb5a2",
                "question": "We have hundreds of available boats, and everyday new listings available",
                "ordinal": 1,
                "text": "Let us know what you are interested in, and we will do the rest",
                "type": "horizontal",
                "answerType": "information-only",
                "buttonId": "3fbf796c-f078-4926-9641-95893584d123",
                "buttonText": "Lets do this!",
                "validationRequired": false,
                "validationRule": "",
                "answers": []
            }
        ]
    },
    {
        "id": "2",
        "name": "Test form 2",
        "description": "Form description 2",
        "questions": [
            {
                "id": "402a1459-f7cf-42f7-8d56-dfc100adb5a2",
                "question": "We have hundreds of available boats, and everyday new listings available",
                "ordinal": 1,
                "text": "Let us know what you are interested in, and we will do the rest",
                "type": "horizontal",
                "answerType": "information-only",
                "buttonId": "3fbf796c-f078-4926-9641-95893584d123",
                "buttonText": "Lets do this!",
                "validationRequired": false,
                "validationRule": "",
                "answers": []
            }
        ]
    }
]
